wangticketyes24/__init__.py
wangticketyes24-1.7.dist-info/DESCRIPTION.rst
wangticketyes24-1.7.dist-info/METADATA
wangticketyes24-1.7.dist-info/RECORD
wangticketyes24-1.7.dist-info/WHEEL
wangticketyes24-1.7.dist-info/metadata.json
wangticketyes24-1.7.dist-info/top_level.txt
