Metadata-Version: 2.0
Name: wangticketyes24
Version: 1.7
Summary: wangticket for y
Home-page: https://gitlab.com/wangticket/yes24-ticket
Author: Wangticket
Author-email: wangticket77@gmail.com
License: UNKNOWN
Platform: UNKNOWN
Classifier: Programming Language :: Python :: 3
Classifier: License :: OSI Approved :: MIT License
Classifier: Operating System :: OS Independent
Requires-Python: >=3
Requires-Dist: beautifulsoup4
Requires-Dist: selenium (==3.141.0)
Requires-Dist: urllib3 (==1.25.6)
Requires-Dist: requests
